[
  {
    "epoch": 0,
    "timestamp": "0:00:02.297122",
    "metrics": {
      "train": {
        "class_metrics": {
          "top1_accuracy": 0.5767434100767435,
          "top5_accuracy": 0.7487487487487487
        },
        "loss_metrics": {
          "loss": 733.928389787674
        }
      }
    }
  },
  {
    "epoch": 1,
    "timestamp": "0:00:03.221576",
    "metrics": {
      "train": {
        "class_metrics": {
          "top1_accuracy": 0.9806473139806473,
          "top5_accuracy": 1.0
        },
        "loss_metrics": {
          "loss": 344.6529747247696
        }
      }
    }
  },
  {
    "epoch": 2,
    "timestamp": "0:00:03.727093",
    "metrics": {
      "train": {
        "class_metrics": {
          "top1_accuracy": 0.9913246579913246,
          "top5_accuracy": 1.0
        },
        "loss_metrics": {
          "loss": 178.88559710979462
        }
      }
    }
  },
  {
    "epoch": 3,
    "timestamp": "0:00:04.758262",
    "metrics": {
      "train": {
        "class_metrics": {
          "top1_accuracy": 0.9988321654988321,
          "top5_accuracy": 1.0
        },
        "loss_metrics": {
          "loss": 109.18645572662354
        }
      }
    }
  },
  {
    "epoch": 4,
    "timestamp": "0:00:05.258998",
    "metrics": {
      "train": {
        "class_metrics": {
          "top1_accuracy": 0.9993326659993327,
          "top5_accuracy": 1.0
        },
        "loss_metrics": {
          "loss": 74.95905055105686
        }
      }
    }
  },
  {
    "epoch": 5,
    "timestamp": "0:00:05.780618",
    "metrics": {
      "train": {
        "class_metrics": {
          "top1_accuracy": 1.0,
          "top5_accuracy": 1.0
        },
        "loss_metrics": {
          "loss": 55.338143944740295
        }
      }
    }
  },
  {
    "epoch": 6,
    "timestamp": "0:00:06.804571",
    "metrics": {
      "train": {
        "class_metrics": {
          "top1_accuracy": 1.0,
          "top5_accuracy": 1.0
        },
        "loss_metrics": {
          "loss": 42.93609781563282
        }
      }
    }
  },
  {
    "epoch": 7,
    "timestamp": "0:00:07.345362",
    "metrics": {
      "train": {
        "class_metrics": {
          "top1_accuracy": 1.0,
          "top5_accuracy": 1.0
        },
        "loss_metrics": {
          "loss": 34.66790869832039
        }
      }
    }
  },
  {
    "epoch": 8,
    "timestamp": "0:00:08.218500",
    "metrics": {
      "train": {
        "class_metrics": {
          "top1_accuracy": 1.0,
          "top5_accuracy": 1.0
        },
        "loss_metrics": {
          "loss": 28.824233204126358
        }
      }
    }
  },
  {
    "epoch": 9,
    "timestamp": "0:00:08.808056",
    "metrics": {
      "train": {
        "class_metrics": {
          "top1_accuracy": 1.0,
          "top5_accuracy": 1.0
        },
        "loss_metrics": {
          "loss": 24.363412216305733
        }
      }
    }
  },
  {
    "epoch": 10,
    "timestamp": "0:00:09.340890",
    "metrics": {
      "train": {
        "class_metrics": {
          "top1_accuracy": 1.0,
          "top5_accuracy": 1.0
        },
        "loss_metrics": {
          "loss": 20.901794388890266
        }
      }
    }
  },
  {
    "epoch": 11,
    "timestamp": "0:00:10.414139",
    "metrics": {
      "train": {
        "class_metrics": {
          "top1_accuracy": 1.0,
          "top5_accuracy": 1.0
        },
        "loss_metrics": {
          "loss": 18.273775674402714
        }
      }
    }
  },
  {
    "epoch": 12,
    "timestamp": "0:00:10.936284",
    "metrics": {
      "train": {
        "class_metrics": {
          "top1_accuracy": 1.0,
          "top5_accuracy": 1.0
        },
        "loss_metrics": {
          "loss": 16.19262331351638
        }
      }
    }
  },
  {
    "epoch": 13,
    "timestamp": "0:00:11.586402",
    "metrics": {
      "train": {
        "class_metrics": {
          "top1_accuracy": 1.0,
          "top5_accuracy": 1.0
        },
        "loss_metrics": {
          "loss": 14.511801581829786
        }
      }
    }
  },
  {
    "epoch": 14,
    "timestamp": "0:00:12.384238",
    "metrics": {
      "train": {
        "class_metrics": {
          "top1_accuracy": 1.0,
          "top5_accuracy": 1.0
        },
        "loss_metrics": {
          "loss": 13.151749450713396
        }
      }
    }
  },
  {
    "epoch": 15,
    "timestamp": "0:00:12.920384",
    "metrics": {
      "train": {
        "class_metrics": {
          "top1_accuracy": 1.0,
          "top5_accuracy": 1.0
        },
        "loss_metrics": {
          "loss": 12.053638558834791
        }
      }
    }
  },
  {
    "epoch": 16,
    "timestamp": "0:00:13.981442",
    "metrics": {
      "train": {
        "class_metrics": {
          "top1_accuracy": 1.0,
          "top5_accuracy": 1.0
        },
        "loss_metrics": {
          "loss": 11.065141880884767
        }
      }
    }
  },
  {
    "epoch": 17,
    "timestamp": "0:00:14.525475",
    "metrics": {
      "train": {
        "class_metrics": {
          "top1_accuracy": 1.0,
          "top5_accuracy": 1.0
        },
        "loss_metrics": {
          "loss": 10.328494809567928
        }
      }
    }
  },
  {
    "epoch": 18,
    "timestamp": "0:00:15.309753",
    "metrics": {
      "train": {
        "class_metrics": {
          "top1_accuracy": 1.0,
          "top5_accuracy": 1.0
        },
        "loss_metrics": {
          "loss": 9.599294696003199
        }
      }
    }
  },
  {
    "epoch": 19,
    "timestamp": "0:00:15.969624",
    "metrics": {
      "train": {
        "class_metrics": {
          "top1_accuracy": 1.0,
          "top5_accuracy": 1.0
        },
        "loss_metrics": {
          "loss": 8.98773693293333
        }
      }
    }
  },
  {
    "epoch": 20,
    "timestamp": "0:00:16.494636",
    "metrics": {
      "train": {
        "class_metrics": {
          "top1_accuracy": 1.0,
          "top5_accuracy": 1.0
        },
        "loss_metrics": {
          "loss": 8.53918488509953
        }
      }
    }
  },
  {
    "epoch": 21,
    "timestamp": "0:00:17.509333",
    "metrics": {
      "train": {
        "class_metrics": {
          "top1_accuracy": 1.0,
          "top5_accuracy": 1.0
        },
        "loss_metrics": {
          "loss": 8.050772732123733
        }
      }
    }
  },
  {
    "epoch": 22,
    "timestamp": "0:00:18.025121",
    "metrics": {
      "train": {
        "class_metrics": {
          "top1_accuracy": 1.0,
          "top5_accuracy": 1.0
        },
        "loss_metrics": {
          "loss": 7.639653606340289
        }
      }
    }
  },
  {
    "epoch": 23,
    "timestamp": "0:00:18.569137",
    "metrics": {
      "train": {
        "class_metrics": {
          "top1_accuracy": 1.0,
          "top5_accuracy": 1.0
        },
        "loss_metrics": {
          "loss": 7.299832137301564
        }
      }
    }
  },
  {
    "epoch": 24,
    "timestamp": "0:00:19.516938",
    "metrics": {
      "train": {
        "class_metrics": {
          "top1_accuracy": 1.0,
          "top5_accuracy": 1.0
        },
        "loss_metrics": {
          "loss": 6.978301862254739
        }
      }
    }
  },
  {
    "epoch": 25,
    "timestamp": "0:00:20.055316",
    "metrics": {
      "train": {
        "class_metrics": {
          "top1_accuracy": 1.0,
          "top5_accuracy": 1.0
        },
        "loss_metrics": {
          "loss": 6.684319019317627
        }
      }
    }
  },
  {
    "epoch": 26,
    "timestamp": "0:00:20.559559",
    "metrics": {
      "train": {
        "class_metrics": {
          "top1_accuracy": 1.0,
          "top5_accuracy": 1.0
        },
        "loss_metrics": {
          "loss": 6.417729217559099
        }
      }
    }
  },
  {
    "epoch": 27,
    "timestamp": "0:00:21.086199",
    "metrics": {
      "train": {
        "class_metrics": {
          "top1_accuracy": 1.0,
          "top5_accuracy": 1.0
        },
        "loss_metrics": {
          "loss": 6.167777368798852
        }
      }
    }
  },
  {
    "epoch": 28,
    "timestamp": "0:00:21.639470",
    "metrics": {
      "train": {
        "class_metrics": {
          "top1_accuracy": 1.0,
          "top5_accuracy": 1.0
        },
        "loss_metrics": {
          "loss": 5.980079023167491
        }
      }
    }
  },
  {
    "epoch": 29,
    "timestamp": "0:00:22.330479",
    "metrics": {
      "train": {
        "class_metrics": {
          "top1_accuracy": 1.0,
          "top5_accuracy": 1.0
        },
        "loss_metrics": {
          "loss": 5.730890056118369
        }
      }
    }
  },
  {
    "epoch": 30,
    "timestamp": "0:00:22.855141",
    "metrics": {
      "train": {
        "class_metrics": {
          "top1_accuracy": 1.0,
          "top5_accuracy": 1.0
        },
        "loss_metrics": {
          "loss": 5.530155396088958
        }
      }
    }
  },
  {
    "epoch": 31,
    "timestamp": "0:00:23.504035",
    "metrics": {
      "train": {
        "class_metrics": {
          "top1_accuracy": 1.0,
          "top5_accuracy": 1.0
        },
        "loss_metrics": {
          "loss": 5.358980365097523
        }
      }
    }
  },
  {
    "epoch": 32,
    "timestamp": "0:00:24.003449",
    "metrics": {
      "train": {
        "class_metrics": {
          "top1_accuracy": 1.0,
          "top5_accuracy": 1.0
        },
        "loss_metrics": {
          "loss": 5.194296855479479
        }
      }
    }
  },
  {
    "epoch": 33,
    "timestamp": "0:00:24.509504",
    "metrics": {
      "train": {
        "class_metrics": {
          "top1_accuracy": 1.0,
          "top5_accuracy": 1.0
        },
        "loss_metrics": {
          "loss": 5.030392242595553
        }
      }
    }
  },
  {
    "epoch": 34,
    "timestamp": "0:00:25.163215",
    "metrics": {
      "train": {
        "class_metrics": {
          "top1_accuracy": 1.0,
          "top5_accuracy": 1.0
        },
        "loss_metrics": {
          "loss": 4.896384098567069
        }
      }
    }
  },
  {
    "epoch": 35,
    "timestamp": "0:00:25.683242",
    "metrics": {
      "train": {
        "class_metrics": {
          "top1_accuracy": 1.0,
          "top5_accuracy": 1.0
        },
        "loss_metrics": {
          "loss": 4.758996577933431
        }
      }
    }
  },
  {
    "epoch": 36,
    "timestamp": "0:00:26.195792",
    "metrics": {
      "train": {
        "class_metrics": {
          "top1_accuracy": 1.0,
          "top5_accuracy": 1.0
        },
        "loss_metrics": {
          "loss": 4.618624845519662
        }
      }
    }
  },
  {
    "epoch": 37,
    "timestamp": "0:00:26.892266",
    "metrics": {
      "train": {
        "class_metrics": {
          "top1_accuracy": 1.0,
          "top5_accuracy": 1.0
        },
        "loss_metrics": {
          "loss": 4.502126247622073
        }
      }
    }
  },
  {
    "epoch": 38,
    "timestamp": "0:00:27.385024",
    "metrics": {
      "train": {
        "class_metrics": {
          "top1_accuracy": 1.0,
          "top5_accuracy": 1.0
        },
        "loss_metrics": {
          "loss": 4.388890421949327
        }
      }
    }
  },
  {
    "epoch": 39,
    "timestamp": "0:00:27.904285",
    "metrics": {
      "train": {
        "class_metrics": {
          "top1_accuracy": 1.0,
          "top5_accuracy": 1.0
        },
        "loss_metrics": {
          "loss": 4.253456911072135
        }
      }
    }
  },
  {
    "epoch": 40,
    "timestamp": "0:00:28.612199",
    "metrics": {
      "train": {
        "class_metrics": {
          "top1_accuracy": 1.0,
          "top5_accuracy": 1.0
        },
        "loss_metrics": {
          "loss": 4.170878514647484
        }
      }
    }
  },
  {
    "epoch": 41,
    "timestamp": "0:00:29.124919",
    "metrics": {
      "train": {
        "class_metrics": {
          "top1_accuracy": 1.0,
          "top5_accuracy": 1.0
        },
        "loss_metrics": {
          "loss": 4.071847626939416
        }
      }
    }
  },
  {
    "epoch": 42,
    "timestamp": "0:00:29.635269",
    "metrics": {
      "train": {
        "class_metrics": {
          "top1_accuracy": 1.0,
          "top5_accuracy": 1.0
        },
        "loss_metrics": {
          "loss": 3.9817979112267494
        }
      }
    }
  },
  {
    "epoch": 43,
    "timestamp": "0:00:30.326821",
    "metrics": {
      "train": {
        "class_metrics": {
          "top1_accuracy": 1.0,
          "top5_accuracy": 1.0
        },
        "loss_metrics": {
          "loss": 3.906546317972243
        }
      }
    }
  },
  {
    "epoch": 44,
    "timestamp": "0:00:30.854387",
    "metrics": {
      "train": {
        "class_metrics": {
          "top1_accuracy": 1.0,
          "top5_accuracy": 1.0
        },
        "loss_metrics": {
          "loss": 3.8190027847886086
        }
      }
    }
  },
  {
    "epoch": 45,
    "timestamp": "0:00:31.503905",
    "metrics": {
      "train": {
        "class_metrics": {
          "top1_accuracy": 1.0,
          "top5_accuracy": 1.0
        },
        "loss_metrics": {
          "loss": 3.751265397295356
        }
      }
    }
  },
  {
    "epoch": 46,
    "timestamp": "0:00:32.031265",
    "metrics": {
      "train": {
        "class_metrics": {
          "top1_accuracy": 1.0,
          "top5_accuracy": 1.0
        },
        "loss_metrics": {
          "loss": 3.6743477741256356
        }
      }
    }
  },
  {
    "epoch": 47,
    "timestamp": "0:00:32.529661",
    "metrics": {
      "train": {
        "class_metrics": {
          "top1_accuracy": 1.0,
          "top5_accuracy": 1.0
        },
        "loss_metrics": {
          "loss": 3.605966337956488
        }
      }
    }
  },
  {
    "epoch": 48,
    "timestamp": "0:00:33.220587",
    "metrics": {
      "train": {
        "class_metrics": {
          "top1_accuracy": 1.0,
          "top5_accuracy": 1.0
        },
        "loss_metrics": {
          "loss": 3.5485914843156934
        }
      }
    }
  }
]